LICENSE
README.md
pyproject.toml
setup.py
bTagScript/__init__.py
bTagScript/exceptions.py
bTagScript/interpreter.py
bTagScript/utils.py
bTagScript/verb.py
bTagScript.egg-info/PKG-INFO
bTagScript.egg-info/SOURCES.txt
bTagScript.egg-info/dependency_links.txt
bTagScript.egg-info/requires.txt
bTagScript.egg-info/top_level.txt
bTagScript/adapter/__init__.py
bTagScript/adapter/discord_adapters.py
bTagScript/adapter/function_adapter.py
bTagScript/adapter/int_adapter.py
bTagScript/adapter/object_adapter.py
bTagScript/adapter/string_adapter.py
bTagScript/block/__init__.py
bTagScript/block/break_block.py
bTagScript/block/comment_block.py
bTagScript/block/control_block.py
bTagScript/block/counting_blocks.py
bTagScript/block/digitshorthand_block.py
bTagScript/block/helpers.py
bTagScript/block/math_blocks.py
bTagScript/block/random_block.py
bTagScript/block/range_block.py
bTagScript/block/replace_block.py
bTagScript/block/stop_block.py
bTagScript/block/strf_block.py
bTagScript/block/url_blocks.py
bTagScript/block/var_block.py
bTagScript/block/vargetter_blocks.py
bTagScript/block/discord_blocks/__init__.py
bTagScript/block/discord_blocks/command_block.py
bTagScript/block/discord_blocks/cooldown_block.py
bTagScript/block/discord_blocks/delete_block.py
bTagScript/block/discord_blocks/embed_block.py
bTagScript/block/discord_blocks/override_block.py
bTagScript/block/discord_blocks/react_block.py
bTagScript/block/discord_blocks/redirect_block.py
bTagScript/block/discord_blocks/requirement_blocks.py
bTagScript/block/util_blocks/__init__.py
bTagScript/block/util_blocks/debug_block.py
bTagScript/interface/__init__.py
bTagScript/interface/adapter.py
bTagScript/interface/block.py