Metadata-Version: 2.1
Name: bTagScript
Version: 3.1.5
Summary: An easy drop in user-provided Templating system.
Home-page: https://github.com/Leg3ndary/bTagScript
Author: Leg3ndary
Author-email: bleg3ndary@gmail.com
Maintainer: Leg3ndary
Maintainer-email: bleg3ndary@gmail.com
License: Creative Commons Attribution 4.0 International License
Project-URL: Documentation, https://btagscript.readthedocs.io/
Keywords: tagscript
Platform: UNKNOWN
Classifier: Development Status :: 5 - Production/Stable
Classifier: Intended Audience :: Developers
Classifier: License :: Freely Distributable
Classifier: Natural Language :: English
Classifier: Operating System :: OS Independent
Classifier: Programming Language :: Python :: 3.8
License-File: LICENSE
